hyssop_aiohttp/__init__.py
hyssop_aiohttp/__main__.py
hyssop_aiohttp/command.py
hyssop_aiohttp/server.py
hyssop_aiohttp/component/__init__.py
hyssop_aiohttp/component/aio_client.py
hyssop_aiohttp-0.0.7.dist-info/LICENSE
hyssop_aiohttp-0.0.7.dist-info/METADATA
hyssop_aiohttp-0.0.7.dist-info/WHEEL
hyssop_aiohttp-0.0.7.dist-info/top_level.txt
hyssop_aiohttp-0.0.7.dist-info/RECORD
