Metadata-Version: 2.1
Name: hyssop-aiohttp
Version: 0.0.7
Summary: Extended hyssop components and utilities
Home-page: https://github.com/hsky77/hyssop
Author: hsky77
Author-email: howardlkung@gmail.com
License: MIT License
Platform: UNKNOWN
Classifier: Programming Language :: Python :: 3
Classifier: Programming Language :: Python :: 3.6
Classifier: Programming Language :: Python :: 3.7
Classifier: Programming Language :: Python :: 3.8
Classifier: License :: OSI Approved :: MIT License
Classifier: Operating System :: OS Independent
Requires-Python: >=3.6
License-File: LICENSE
Requires-Dist: hyssop (>=1.1.6)
Requires-Dist: aiohttp (==3.7.3)
Requires-Dist: aiohttp-cors (==0.7.0)
Requires-Dist: aiohttp-swagger (==1.0.15)
